specmem/__init__.py
specmem/py.typed
specmem/adapters/__init__.py
specmem/adapters/base.py
specmem/adapters/claude.py
specmem/adapters/cursor.py
specmem/adapters/kiro.py
specmem/adapters/power.py
specmem/adapters/registry.py
specmem/adapters/speckit.py
specmem/adapters/tessl.py
specmem/agentx/__init__.py
specmem/agentx/pack_builder.py
specmem/cli/__init__.py
specmem/cli/cov.py
specmem/cli/demo.py
specmem/cli/export.py
specmem/cli/guidelines.py
specmem/cli/kiro_config.py
specmem/cli/lifecycle.py
specmem/cli/main.py
specmem/cli/sessions.py
specmem/client/__init__.py
specmem/client/client.py
specmem/client/exceptions.py
specmem/client/models.py
specmem/client/proposals.py
specmem/context/__init__.py
specmem/context/api.py
specmem/context/endpoints.py
specmem/context/estimator.py
specmem/context/formatter.py
specmem/context/optimizer.py
specmem/context/profiles.py
specmem/core/__init__.py
specmem/core/config.py
specmem/core/exceptions.py
specmem/core/mappings.py
specmem/core/memory_bank.py
specmem/core/specir.py
specmem/coverage/__init__.py
specmem/coverage/engine.py
specmem/coverage/extractor.py
specmem/coverage/matcher.py
specmem/coverage/models.py
specmem/coverage/scanner.py
specmem/diff/__init__.py
specmem/diff/models.py
specmem/diff/specdiff.py
specmem/diff/storage.py
specmem/export/__init__.py
specmem/export/conflicts.py
specmem/export/exporter.py
specmem/export/filters.py
specmem/export/history.py
specmem/export/models.py
specmem/graph/__init__.py
specmem/graph/builder.py
specmem/graph/models.py
specmem/guidelines/__init__.py
specmem/guidelines/aggregator.py
specmem/guidelines/converter.py
specmem/guidelines/models.py
specmem/guidelines/parser.py
specmem/guidelines/samples.py
specmem/guidelines/scanner.py
specmem/health/__init__.py
specmem/health/engine.py
specmem/health/models.py
specmem/hooks/__init__.py
specmem/hooks/generator.py
specmem/impact/__init__.py
specmem/impact/analyzer.py
specmem/impact/builder.py
specmem/impact/graph.py
specmem-0.1.4.dist-info/METADATA
specmem-0.1.4.dist-info/WHEEL
specmem-0.1.4.dist-info/entry_points.txt
specmem-0.1.4.dist-info/licenses/LICENSE
specmem-0.1.4.dist-info/RECORD
