Metadata-Version: 2.4
Name: specmem
Version: 0.1.4
Summary: Unified, embeddable memory layer for AI coding agents built on Spec-Driven Development metadata
Project-URL: Homepage, https://github.com/SuperagenticAI/specmem
Project-URL: Documentation, https://superagenticai.github.io/specmem/
Project-URL: Repository, https://github.com/SuperagenticAI/specmem.git
Project-URL: Issues, https://github.com/SuperagenticAI/specmem/issues
Project-URL: Changelog, https://github.com/SuperagenticAI/specmem/blob/main/CHANGELOG.md
Author-email: Shashi Jagtap <shashi@super-agentic.ai>, Shashi Jagtap <shashikant.jagtap@icloud.com>
Maintainer-email: Shashi Jagtap <team@super-agentic.ai>, Shashi Jagtap <shashikant.jagtap@icloud.com>
License-Expression: AGPL-3.0-or-later
License-File: LICENSE
Keywords: agents,ai,coding-agents,context-management,developer-tools,embeddings,llm,memory,rag,spec-driven-development,specifications,vector-database
Classifier: Development Status :: 4 - Beta
Classifier: Environment :: Console
Classifier: Framework :: Pytest
Classifier: Intended Audience :: Developers
Classifier: License :: OSI Approved :: GNU Affero General Public License v3 or later (AGPLv3+)
Classifier: Operating System :: OS Independent
Classifier: Programming Language :: Python :: 3
Classifier: Programming Language :: Python :: 3.11
Classifier: Programming Language :: Python :: 3.12
Classifier: Programming Language :: Python :: 3.13
Classifier: Topic :: Scientific/Engineering :: Artificial Intelligence
Classifier: Topic :: Software Development :: Libraries :: Python Modules
Classifier: Topic :: Software Development :: Quality Assurance
Classifier: Topic :: Software Development :: Testing
Classifier: Typing :: Typed
Requires-Python: >=3.11
Requires-Dist: click>=8.1.0
Requires-Dist: fastapi>=0.109.0
Requires-Dist: jinja2>=3.1.0
Requires-Dist: numpy>=1.24.0
Requires-Dist: pydantic>=2.0.0
Requires-Dist: pyyaml>=6.0.0
Requires-Dist: rich>=13.0.0
Requires-Dist: tomli-w>=1.0.0
Requires-Dist: tomli>=2.0.0; python_version < '3.11'
Requires-Dist: typer>=0.9.0
Requires-Dist: uvicorn>=0.27.0
Requires-Dist: websockets>=12.0
Provides-Extra: all
Requires-Dist: chromadb>=0.4.0; extra == 'all'
Requires-Dist: google-generativeai>=0.3.0; extra == 'all'
Requires-Dist: hypothesis>=6.98.0; extra == 'all'
Requires-Dist: lancedb>=0.4.0; extra == 'all'
Requires-Dist: mkdocs-material>=9.5.0; extra == 'all'
Requires-Dist: mkdocs>=1.5.0; extra == 'all'
Requires-Dist: mkdocstrings[python]>=0.24.0; extra == 'all'
Requires-Dist: mypy>=1.8.0; extra == 'all'
Requires-Dist: openai>=1.0.0; extra == 'all'
Requires-Dist: pre-commit>=3.6.0; extra == 'all'
Requires-Dist: pyarrow>=14.0.0; extra == 'all'
Requires-Dist: pymdown-extensions>=10.0.0; extra == 'all'
Requires-Dist: pytest-asyncio>=0.23.0; extra == 'all'
Requires-Dist: pytest-benchmark>=4.0.0; extra == 'all'
Requires-Dist: pytest-cov>=4.1.0; extra == 'all'
Requires-Dist: pytest>=8.0.0; extra == 'all'
Requires-Dist: qdrant-client>=1.7.0; extra == 'all'
Requires-Dist: ruff>=0.3.0; extra == 'all'
Requires-Dist: sentence-transformers>=2.2.0; extra == 'all'
Requires-Dist: together>=0.2.0; extra == 'all'
Requires-Dist: types-toml>=0.10.8; extra == 'all'
Provides-Extra: chroma
Requires-Dist: chromadb>=0.4.0; extra == 'chroma'
Provides-Extra: cloud
Requires-Dist: google-generativeai>=0.3.0; extra == 'cloud'
Requires-Dist: openai>=1.0.0; extra == 'cloud'
Requires-Dist: together>=0.2.0; extra == 'cloud'
Provides-Extra: dev
Requires-Dist: hypothesis>=6.98.0; extra == 'dev'
Requires-Dist: mypy>=1.8.0; extra == 'dev'
Requires-Dist: pre-commit>=3.6.0; extra == 'dev'
Requires-Dist: pytest-asyncio>=0.23.0; extra == 'dev'
Requires-Dist: pytest-benchmark>=4.0.0; extra == 'dev'
Requires-Dist: pytest-cov>=4.1.0; extra == 'dev'
Requires-Dist: pytest>=8.0.0; extra == 'dev'
Requires-Dist: ruff>=0.3.0; extra == 'dev'
Requires-Dist: types-toml>=0.10.8; extra == 'dev'
Provides-Extra: docs
Requires-Dist: mkdocs-material>=9.5.0; extra == 'docs'
Requires-Dist: mkdocs>=1.5.0; extra == 'docs'
Requires-Dist: mkdocstrings[python]>=0.24.0; extra == 'docs'
Requires-Dist: pymdown-extensions>=10.0.0; extra == 'docs'
Provides-Extra: google
Requires-Dist: google-generativeai>=0.3.0; extra == 'google'
Provides-Extra: local
Requires-Dist: lancedb>=0.4.0; extra == 'local'
Requires-Dist: pyarrow>=14.0.0; extra == 'local'
Requires-Dist: sentence-transformers>=2.2.0; extra == 'local'
Provides-Extra: openai
Requires-Dist: openai>=1.0.0; extra == 'openai'
Provides-Extra: qdrant
Requires-Dist: qdrant-client>=1.7.0; extra == 'qdrant'
Provides-Extra: together
Requires-Dist: together>=0.2.0; extra == 'together'
Provides-Extra: ui
